{"commit_hash": "f65299439b7debe879d9342b54e85a25bbf871b5", "date": 1623980943000, "env_name": "conda-py3.8-Cython0.29.21-jinja2-matplotlib-numba-numexpr-numpy-odfpy-openpyxl-pytables-pytest-scipy-sqlalchemy-xlrd-xlsxwriter-xlwt", "params": {"arch": "x86_64", "cpu": "Intel(R) Xeon(R) E-2174G CPU @ 3.80GHz", "machine": "T3630", "num_cpu": "4", "os": "Linux 5.4.72-microsoft-standard-WSL2", "ram": "16GB", "python": "3.8", "Cython": "0.29.21", "jinja2": "", "matplotlib": "", "numba": "", "numexpr": "", "numpy": "", "odfpy": "", "openpyxl": "", "pytables": "", "pytest": "", "scipy": "", "sqlalchemy": "", "xlrd": "", "xlsxwriter": "", "xlwt": ""}, "python": "3.8", "requirements": {"Cython": "0.29.21", "jinja2": "", "matplotlib": "", "numba": "", "numexpr": "", "numpy": "", "odfpy": "", "openpyxl": "", "pytables": "", "pytest": "", "scipy": "", "sqlalchemy": "", "xlrd": "", "xlsxwriter": "", "xlwt": ""}, "env_vars": {}, "result_columns": ["result", "params", "version", "started_at", "duration", "stats_ci_99_a", "stats_ci_99_b", "stats_q_25", "stats_q_75", "stats_number", "stats_repeat", "samples", "profile"], "results": {"index_object.IntervalIndexMethod.time_intersection": [[0.0020999000001514405, 0.2876943499995832], [["1000", "100000"]], "4211da5ac938e20dc8e3ebad85e3fd809e9b9485898f7bc9fa4b78bf51836ba1", 1624891665877, null, [0.002037, 0.28335], [0.0021779, 0.32204], [0.0020925, 0.28406], [0.0021229, 0.30833], [6, 1], [10, 10]], "index_object.IntervalIndexMethod.time_intersection_both_duplicate": [[0.0030900249998921936, 0.22595485000056215], [["1000", "100000"]], "51c27b25f860d486d8b165a9a8fff37e4de68c2b0a193957783434e9151daaaa", 1624891669144, null, [0.0030099, 0.22162], [0.0032691, 0.2684], [0.0030605, 0.22322], [0.0031222, 0.22883], [4, 1], [10, 10]], "index_object.IntervalIndexMethod.time_intersection_one_duplicate": [[0.002359490000162623, 0.1714936000007583], [["1000", "100000"]], "d690ff28419653e49b71207cafa08bd0c7e2901de3773c422f3c20c5659c70da", 1624891671858, null, [0.0022469, 0.16167], [0.0024204, 0.18912], [0.0022837, 0.16451], [0.0023828, 0.18334], [5, 1], [10, 10]]}, "durations": {}, "version": 2}